doc/Makefile
doc/api.rst
doc/conf.py
doc/index.rst
doc/_templates/autosummary/class.rst
doc/_templates/autosummary/function.rst
examples/README.txt
examples/evoked_ers_source_power.py
mne_gui_addons/__init__.py
mne_gui_addons/_core.py
mne_gui_addons/_ieeg_locate.py
mne_gui_addons/_vol_stc.py
mne_gui_addons/conftest.py
mne_gui_addons/_utils/__init__.py
mne_gui_addons/_utils/docs.py
mne_gui_addons/tests/test_basic.py
mne_gui_addons/tests/test_core.py
mne_gui_addons/tests/test_ieeg_locate.py
mne_gui_addons/tests/test_vol_stc.py
mne_gui_addons-0.1.dist-info/LICENSE
mne_gui_addons-0.1.dist-info/METADATA
mne_gui_addons-0.1.dist-info/WHEEL
mne_gui_addons-0.1.dist-info/top_level.txt
mne_gui_addons-0.1.dist-info/RECORD
