Metadata-Version: 2.1
Name: mne-gui-addons
Version: 0.1
Summary: MNE-Python GUI addons.
Author: Eric Larson
Author-email: Alex Rockhill <aprockhill206@gmail.com>
License: BSD 3-Clause License
Project-URL: homepage, https://github.com/mne-tools/mne-gui-addons
Project-URL: repository, https://github.com/mne-tools/mne-gui-addons
Project-URL: changelog, https://github.com/mne-tools/mne-gui-addons/releases
Keywords: science,neuroscience,psychology
Classifier: Intended Audience :: Science/Research
Classifier: Programming Language :: Python
Requires-Python: >=3.8
License-File: LICENSE
Requires-Dist: packaging
Requires-Dist: qtpy
Requires-Dist: pyvista
Requires-Dist: pyvistaqt
Requires-Dist: mne
Requires-Dist: nibabel
Requires-Dist: dipy (>=1.4)
Requires-Dist: traitlets
Requires-Dist: setuptools (>=65)
Provides-Extra: tests
Requires-Dist: pytest ; extra == 'tests'
Requires-Dist: pytest-cov ; extra == 'tests'
Requires-Dist: black ; extra == 'tests'
